slack_python_logging/__init__.py
slack_python_logging/formatter.py
slack_python_logging/handler.py
slack_python_logging/logrecord.py
slack_python_logging/slack_logger.py
slack_python_logging-1.3.0.dist-info/DESCRIPTION.rst
slack_python_logging-1.3.0.dist-info/METADATA
slack_python_logging-1.3.0.dist-info/RECORD
slack_python_logging-1.3.0.dist-info/WHEEL
slack_python_logging-1.3.0.dist-info/metadata.json
slack_python_logging-1.3.0.dist-info/top_level.txt
