Metadata-Version: 2.0
Name: slack-python-logging
Version: 1.3.0
Summary: Module for logging to a Slack Channel with Webhooks
Home-page: https://github.com/neoliberal/slack_python_logging
Author: Abhi Agarwal
Author-email: abhi@neoliber.al
License: MIT
Keywords: reddit,slack python_logging
Platform: UNKNOWN
Classifier: Development Status :: 4 - Beta
Classifier: Environment :: Console
Classifier: Intended Audience :: Developers
Classifier: License :: OSI Approved :: MIT License
Classifier: Natural Language :: English
Classifier: Operating System :: POSIX :: Linux
Classifier: Programming Language :: Python :: 3 :: Only
Classifier: Programming Language :: Python :: Implementation :: CPython
Classifier: Topic :: Software Development :: Libraries :: Python Modules
Requires-Python: >=3
Requires-Dist: systemd-python
